fxpyD365api/__init__.py
fxpyD365api/async_.py
fxpyD365api/base.py
fxpyD365api/exceptions.py
fxpyD365api/factory.py
fxpyD365api/generic.py
fxpyD365api/sync.py
fxpyD365api-2.2.1.dist-info/METADATA
fxpyD365api-2.2.1.dist-info/WHEEL
fxpyD365api-2.2.1.dist-info/top_level.txt
fxpyD365api-2.2.1.dist-info/RECORD
