Metadata-Version: 2.1
Name: fxpyD365api
Version: 2.2.1
Summary: Wrapper classes for working with Dynamics 365 web API entities.
Home-page: https://github.com/flexitdev/fxpyD365api
Author: Flexit developers
Author-email: westma@flexit.no
License: BSD
Classifier: Development Status :: 4 - Beta
Classifier: Environment :: Web Environment
Classifier: Intended Audience :: Developers
Classifier: License :: OSI Approved
Classifier: Operating System :: OS Independent
Classifier: Programming Language :: Python
Requires-Dist: requests>=2.20.0
Requires-Dist: urllib3<3.0.0,>=1.26.0
Requires-Dist: msal
Requires-Dist: aiohttp
